photofinish/__init__.py
photofinish/__main__.py
photofinish/app.py
photofinish/utils.py
photofinish-0.0.1.dist-info/METADATA
photofinish-0.0.1.dist-info/RECORD
photofinish-0.0.1.dist-info/WHEEL
photofinish-0.0.1.dist-info/entry_points.txt
photofinish-0.0.1.dist-info/top_level.txt
