Metadata-Version: 2.1
Name: photofinish
Version: 0.0.1
Summary: Microservice for uploading images and avatars
Home-page: https://github.com/everypony/photofinish
Author: Andriy Kushnir (Orhideous)
Author-email: me@orhideous.name
License: MIT license
Platform: UNKNOWN
Classifier: Development Status :: 4 - Beta
Classifier: Intended Audience :: Developers
Classifier: License :: OSI Approved :: MIT License
Classifier: Natural Language :: English
Classifier: Programming Language :: Python :: 3.6
Classifier: Programming Language :: Python :: 3.7
Requires-Dist: Pillow (==5.3.0)
Requires-Dist: aiofiles (==0.4.0)
Requires-Dist: aiohttp (==3.4.4)
Requires-Dist: aioredis (==1.2.0)
Requires-Dist: click (==7.0)
Requires-Dist: mime (==0.1.0)
Requires-Dist: phpserialize (==1.3)
Requires-Dist: python-magic (==0.4.15)
Requires-Dist: uvloop (==0.11.3)
Requires-Dist: uvloop (==0.11.3)
